fimex/__init__.py
fimex/core/__init__.py
fimex-0.0.1.dist-info/LICENSE
fimex-0.0.1.dist-info/METADATA
fimex-0.0.1.dist-info/WHEEL
fimex-0.0.1.dist-info/entry_points.txt
fimex-0.0.1.dist-info/RECORD
